bond/__init__.py
bond/bond.py
bond/cli.py
bond/config.py
bond/constants.py
bond/metadata_merge.py
bond/validator.py
bond/data/config.yml
bond/testdata/complete/README
bond/testdata/complete/dataset_description.json
bond/testdata/complete/sub-01/ses-phdiff/anat/sub-01_ses-phdiff_T1w.json
bond/testdata/complete/sub-01/ses-phdiff/anat/sub-01_ses-phdiff_T1w.nii.gz
bond/testdata/complete/sub-01/ses-phdiff/dwi/sub-01_ses-phdiff_acq-HASC55AP_dwi.bval
bond/testdata/complete/sub-01/ses-phdiff/dwi/sub-01_ses-phdiff_acq-HASC55AP_dwi.bvec
bond/testdata/complete/sub-01/ses-phdiff/dwi/sub-01_ses-phdiff_acq-HASC55AP_dwi.json
bond/testdata/complete/sub-01/ses-phdiff/dwi/sub-01_ses-phdiff_acq-HASC55AP_dwi.nii.gz
bond/testdata/complete/sub-01/ses-phdiff/fmap/sub-01_ses-phdiff_acq-v4_magnitude1.json
bond/testdata/complete/sub-01/ses-phdiff/fmap/sub-01_ses-phdiff_acq-v4_magnitude1.nii.gz
bond/testdata/complete/sub-01/ses-phdiff/fmap/sub-01_ses-phdiff_acq-v4_magnitude2.json
bond/testdata/complete/sub-01/ses-phdiff/fmap/sub-01_ses-phdiff_acq-v4_magnitude2.nii.gz
bond/testdata/complete/sub-01/ses-phdiff/fmap/sub-01_ses-phdiff_acq-v4_phasediff.json
bond/testdata/complete/sub-01/ses-phdiff/fmap/sub-01_ses-phdiff_acq-v4_phasediff.nii.gz
bond/testdata/complete/sub-01/ses-phdiff/fmap/sub-01_ses-phdiff_dir-PA_epi.json
bond/testdata/complete/sub-01/ses-phdiff/fmap/sub-01_ses-phdiff_dir-PA_epi.nii.gz
bond/testdata/complete/sub-01/ses-phdiff/func/sub-01_ses-phdiff_task-rest_bold.json
bond/testdata/complete/sub-01/ses-phdiff/func/sub-01_ses-phdiff_task-rest_bold.nii.gz
bond/testdata/complete/sub-02/ses-phdiff/anat/sub-02_ses-phdiff_T1w.json
bond/testdata/complete/sub-02/ses-phdiff/anat/sub-02_ses-phdiff_T1w.nii.gz
bond/testdata/complete/sub-02/ses-phdiff/dwi/sub-02_ses-phdiff_acq-HASC55AP_dwi.bval
bond/testdata/complete/sub-02/ses-phdiff/dwi/sub-02_ses-phdiff_acq-HASC55AP_dwi.bvec
bond/testdata/complete/sub-02/ses-phdiff/dwi/sub-02_ses-phdiff_acq-HASC55AP_dwi.json
cubids_bond_fork-0.1.0.dist-info/AUTHORS.rst
cubids_bond_fork-0.1.0.dist-info/LICENSE
cubids_bond_fork-0.1.0.dist-info/METADATA
cubids_bond_fork-0.1.0.dist-info/WHEEL
cubids_bond_fork-0.1.0.dist-info/entry_points.txt
cubids_bond_fork-0.1.0.dist-info/top_level.txt
cubids_bond_fork-0.1.0.dist-info/RECORD
