Metadata-Version: 2.1
Name: cubids-bond-fork
Version: 0.1.0
Summary: BIDS On Disk Editor
Home-page: https://github.com/pennlinc/bond
Author: PennLINC
Author-email: matthew.cieslak@pennmecidine.upenn.edu
License: GNU General Public License v3
Keywords: bond
Platform: UNKNOWN
Classifier: Development Status :: 2 - Pre-Alpha
Classifier: Intended Audience :: Developers
Classifier: Natural Language :: English
Classifier: Programming Language :: Python :: 3
Classifier: Programming Language :: Python :: 3.7
Classifier: Programming Language :: Python :: 3.8
Requires-Python: >=3.5
Provides-Extra: datalad
Provides-Extra: doc
Provides-Extra: tests
Provides-Extra: docs
Provides-Extra: all
